mopidy_tunein/__init__.py
mopidy_tunein/actor.py
mopidy_tunein/ext.conf
mopidy_tunein/translator.py
mopidy_tunein/tunein.py
Mopidy_TuneIn-1.1.0.dist-info/LICENSE
Mopidy_TuneIn-1.1.0.dist-info/METADATA
Mopidy_TuneIn-1.1.0.dist-info/WHEEL
Mopidy_TuneIn-1.1.0.dist-info/entry_points.txt
Mopidy_TuneIn-1.1.0.dist-info/top_level.txt
Mopidy_TuneIn-1.1.0.dist-info/RECORD
